requirements.txt
setup.py
django_bookmark_base/__init__.py
django_bookmark_base/models.py
django_bookmark_base/views.py
django_bookmark_base.egg-info/PKG-INFO
django_bookmark_base.egg-info/SOURCES.txt
django_bookmark_base.egg-info/dependency_links.txt
django_bookmark_base.egg-info/requires.txt
django_bookmark_base.egg-info/top_level.txt