Metadata-Version: 2.1
Name: django-bookmark-base
Version: 2020.7.1
Summary: Django bookmark base models and views
Home-page: https://github.com/andrewp-as-is/django-bookmark-base.py
License: Unlicense
Keywords: django bookmark
Platform: UNKNOWN
Classifier: Framework :: Django
Classifier: License :: Public Domain
Classifier: Operating System :: OS Independent
Classifier: Programming Language :: Python :: 3
